dinocheck/__init__.py
dinocheck/__main__.py
dinocheck/_version.py
dinocheck/cli/__init__.py
dinocheck/cli/console.py
dinocheck/cli/main.py
dinocheck/cli/formatters/__init__.py
dinocheck/cli/formatters/json_formatter.py
dinocheck/cli/formatters/jsonl_formatter.py
dinocheck/cli/formatters/text_formatter.py
dinocheck/core/__init__.py
dinocheck/core/cache.py
dinocheck/core/config.py
dinocheck/core/engine.py
dinocheck/core/interfaces.py
dinocheck/core/logging.py
dinocheck/core/scoring.py
dinocheck/core/workspace.py
dinocheck/core/types/__init__.py
dinocheck/core/types/analysis_result.py
dinocheck/core/types/cache_stats.py
dinocheck/core/types/diff_hunk.py
dinocheck/core/types/file_context.py
dinocheck/core/types/issue.py
dinocheck/core/types/issue_level.py
dinocheck/core/types/llm_call_log.py
dinocheck/core/types/location.py
dinocheck/core/types/rule.py
dinocheck/core/types/rule_trigger.py
dinocheck/llm/__init__.py
dinocheck/llm/schemas.py
dinocheck/llm/prompts/__init__.py
dinocheck/llm/prompts/critic.py
dinocheck/packs/__init__.py
dinocheck/packs/loader.py
dinocheck/packs/_template/rules/example.yaml
dinocheck/packs/django/__init__.py
dinocheck/packs/django/pack.yaml
dinocheck/packs/django/rules/drf/async-blocking-call.yaml
dinocheck/packs/django/rules/drf/default-throttling.yaml
dinocheck/packs/django/rules/drf/missing-permission-classes.yaml
dinocheck/packs/django/rules/drf/model-serializer-mismatch.yaml
dinocheck/packs/django/rules/drf/permission-logic-mismatch.yaml
dinocheck/packs/django/rules/migrations/large-index-migration.yaml
dinocheck/packs/django/rules/migrations/migration-data-loss.yaml
dinocheck/packs/django/rules/migrations/not-null-two-phase.yaml
dinocheck/packs/django/rules/orm/cache-stale-data.yaml
dinocheck/packs/django/rules/orm/missing-select-related.yaml
dinocheck/packs/django/rules/orm/n-plus-one.yaml
dinocheck/packs/django/rules/orm/queryset-performance.yaml
dinocheck/packs/django/rules/orm/signal-hidden-logic.yaml
dinocheck-0.0.4.dist-info/METADATA
dinocheck-0.0.4.dist-info/WHEEL
dinocheck-0.0.4.dist-info/entry_points.txt
dinocheck-0.0.4.dist-info/licenses/LICENSE
dinocheck-0.0.4.dist-info/RECORD
