Metadata-Version: 2.4
Name: dinocheck
Version: 0.0.4
Summary: Your vibe coding companion - LLM-powered code critic for AI-assisted development
Project-URL: Homepage, https://github.com/diegogm/dinocheck
Project-URL: Documentation, https://github.com/diegogm/dinocheck#readme
Project-URL: Repository, https://github.com/diegogm/dinocheck
Project-URL: Issues, https://github.com/diegogm/dinocheck/issues
Project-URL: Changelog, https://github.com/diegogm/dinocheck/blob/main/CHANGELOG.md
Author-email: Diego Garcia <diego@example.com>
Maintainer-email: Diego Garcia <diego@example.com>
License-Expression: MIT
License-File: LICENSE
Keywords: ai-linter,code-quality,code-review,django,llm,vibe-coding
Classifier: Development Status :: 3 - Alpha
Classifier: Environment :: Console
Classifier: Intended Audience :: Developers
Classifier: License :: OSI Approved :: MIT License
Classifier: Operating System :: OS Independent
Classifier: Programming Language :: Python :: 3
Classifier: Programming Language :: Python :: 3.11
Classifier: Programming Language :: Python :: 3.12
Classifier: Programming Language :: Python :: 3.13
Classifier: Topic :: Software Development :: Quality Assurance
Classifier: Topic :: Software Development :: Testing
Classifier: Typing :: Typed
Requires-Python: >=3.11
Requires-Dist: aiofiles>=23.0
Requires-Dist: gitpython>=3.1
Requires-Dist: httpx>=0.23.0
Requires-Dist: litellm>=1.50.0
Requires-Dist: pydantic-settings<3,>=2.0
Requires-Dist: pydantic<3,>=2.0
Requires-Dist: python-dotenv>=1.0
Requires-Dist: pyyaml>=6.0
Requires-Dist: typer>=0.9.0
Provides-Extra: dev
Requires-Dist: build==1.2.2; extra == 'dev'
Requires-Dist: fabric==3.2.2; extra == 'dev'
Requires-Dist: mypy==1.14.1; extra == 'dev'
Requires-Dist: pre-commit==4.0.1; extra == 'dev'
Requires-Dist: pytest-asyncio==0.25.2; extra == 'dev'
Requires-Dist: pytest-cov==6.0.0; extra == 'dev'
Requires-Dist: pytest==8.3.4; extra == 'dev'
Requires-Dist: ruff==0.9.3; extra == 'dev'
Requires-Dist: twine==6.0.1; extra == 'dev'
Requires-Dist: types-pyyaml>=6.0; extra == 'dev'
Provides-Extra: django
Requires-Dist: django<5.1,>=4.2; extra == 'django'
Requires-Dist: djangorestframework<4.0,>=3.14.0; extra == 'django'
